Metadata-Version: 1.1
Name: django-appengine-toolkit
Version: 0.2.0
Summary: Deploy Django projects on Google App Engine with ease
Home-page: https://github.com/masci/django-appengine-toolkit
Author: Massimiliano Pippi
Author-email: mpippi@gmail.com
License: BSD
Keywords: django-appengine-toolkit
Platform: UNKNOWN
Classifier: Development Status :: 2 - Pre-Alpha
Classifier: Framework :: Django
Classifier: Intended Audience :: Developers
Classifier: License :: OSI Approved :: BSD License
Classifier: Natural Language :: English
Classifier: Programming Language :: Python :: 2
Classifier: Programming Language :: Python :: 2.7
